{
  "data": [
    {
      "id": "102922",
      "Id": "102922",
      "TinhId": 10,
      "NGAY_SINH": "03/20/2009",
      "file_name": "",
      "modified_date": "2024-06-19T08:21:26.658519",
      "NAM": "2024",
      "KY_THI": "LOP10",
      "SBD": "102922",
      "HO_TEN": "LƯƠNG MINH SANG",
      "TINH": "HCM",
      "TOAN": 4.75,
      "VAN": 6.5,
      "NGOAI_NGU": 3.75,
      "CHUYEN": -1,
      "TONGDIEM": 15,
      "SOBAODANH": "102922",
      "LI": "",
      "HOA": "",
      "SU": "",
      "DIA": "",
      "NN": 3.75,
      "GDCN": ""
    }
  ],
  "total": 1,
  "success": true
}