{
  "data": [
    {
      "id": "105649",
      "Id": "105649",
      "TinhId": 10,
      "NGAY_SINH": "05/15/2009",
      "file_name": "",
      "modified_date": "2024-06-19T08:21:26.802030",
      "NAM": "2024",
      "KY_THI": "LOP10",
      "SBD": "105649",
      "HO_TEN": "Nguyễn Tùng Vy",
      "TINH": "HCM",
      "TOAN": 7.5,
      "VAN": 7.25,
      "NGOAI_NGU": 7.25,
      "CHUYEN": -1,
      "TONGDIEM": 22,
      "SOBAODANH": "105649",
      "LI": "",
      "HOA": "",
      "SU": "",
      "DIA": "",
      "NN": 7.25,
      "GDCN": ""
    }
  ],
  "total": 1,
  "success": true
}