{
  "data": [
    {
      "id": "106891",
      "Id": "106891",
      "TinhId": 10,
      "NGAY_SINH": "07/08/2009",
      "file_name": "",
      "modified_date": "2024-06-19T08:21:26.860166",
      "NAM": "2024",
      "KY_THI": "LOP10",
      "SBD": "106891",
      "HO_TEN": "Nguyễn Huỳnh Phương Vy",
      "TINH": "HCM",
      "TOAN": 4.25,
      "VAN": 4.75,
      "NGOAI_NGU": 5.25,
      "CHUYEN": -1,
      "TONGDIEM": 14.25,
      "SOBAODANH": "106891",
      "LI": "",
      "HOA": "",
      "SU": "",
      "DIA": "",
      "NN": 5.25,
      "GDCN": ""
    }
  ],
  "total": 1,
  "success": true
}