{
  "data": [
    {
      "id": "107246",
      "Id": "107246",
      "TinhId": 10,
      "NGAY_SINH": "10/31/2008",
      "file_name": "",
      "modified_date": "2024-06-19T08:21:26.933593",
      "NAM": "2024",
      "KY_THI": "LOP10",
      "SBD": "107246",
      "HO_TEN": "Dương Phước Lộc",
      "TINH": "HCM",
      "TOAN": 2.25,
      "VAN": 5.25,
      "NGOAI_NGU": 5,
      "CHUYEN": -1,
      "TONGDIEM": 12.5,
      "SOBAODANH": "107246",
      "LI": "",
      "HOA": "",
      "SU": "",
      "DIA": "",
      "NN": 5,
      "GDCN": ""
    }
  ],
  "total": 1,
  "success": true
}