{
  "data": [
    {
      "id": "107329",
      "Id": "107329",
      "TinhId": 10,
      "NGAY_SINH": "08/16/2009",
      "file_name": "",
      "modified_date": "2024-06-19T08:21:26.931452",
      "NAM": "2024",
      "KY_THI": "LOP10",
      "SBD": "107329",
      "HO_TEN": "Đoàn Hoài Bảo Ngọc",
      "TINH": "HCM",
      "TOAN": 3.5,
      "VAN": 5,
      "NGOAI_NGU": 4.25,
      "CHUYEN": -1,
      "TONGDIEM": 12.75,
      "SOBAODANH": "107329",
      "LI": "",
      "HOA": "",
      "SU": "",
      "DIA": "",
      "NN": 4.25,
      "GDCN": ""
    }
  ],
  "total": 1,
  "success": true
}