{
  "data": [
    {
      "id": "108445",
      "Id": "108445",
      "TinhId": 10,
      "NGAY_SINH": "07/14/2009",
      "file_name": "",
      "modified_date": "2024-06-19T08:21:26.938575",
      "NAM": "2024",
      "KY_THI": "LOP10",
      "SBD": "108445",
      "HO_TEN": "Nguyễn Hà Xuân",
      "TINH": "HCM",
      "TOAN": 3,
      "VAN": 7.5,
      "NGOAI_NGU": 5.75,
      "CHUYEN": -1,
      "TONGDIEM": 16.25,
      "SOBAODANH": "108445",
      "LI": "",
      "HOA": "",
      "SU": "",
      "DIA": "",
      "NN": 5.75,
      "GDCN": ""
    }
  ],
  "total": 1,
  "success": true
}