{
  "data": [
    {
      "id": "109628",
      "Id": "109628",
      "TinhId": 10,
      "NGAY_SINH": "04/18/2009",
      "file_name": "",
      "modified_date": "2024-06-19T08:21:27.188422",
      "NAM": "2024",
      "KY_THI": "LOP10",
      "SBD": "109628",
      "HO_TEN": "Thái Thuỳ Thảo Trân",
      "TINH": "HCM",
      "TOAN": 2.5,
      "VAN": 3,
      "NGOAI_NGU": 2.25,
      "CHUYEN": -1,
      "TONGDIEM": 7.75,
      "SOBAODANH": "109628",
      "LI": "",
      "HOA": "",
      "SU": "",
      "DIA": "",
      "NN": 2.25,
      "GDCN": ""
    }
  ],
  "total": 1,
  "success": true
}