{
  "data": [
    {
      "id": "110452",
      "Id": "110452",
      "TinhId": 11,
      "NGAY_SINH": "03/07/2009",
      "file_name": "",
      "modified_date": "2024-06-19T08:21:27.122515",
      "NAM": "2024",
      "KY_THI": "LOP10",
      "SBD": "110452",
      "HO_TEN": "Nguyễn Ngọc Kim Ngân",
      "TINH": "HCM",
      "TOAN": 2.75,
      "VAN": 4.25,
      "NGOAI_NGU": 4,
      "CHUYEN": -1,
      "TONGDIEM": 11,
      "SOBAODANH": "110452",
      "LI": "",
      "HOA": "",
      "SU": "",
      "DIA": "",
      "NN": 4,
      "GDCN": ""
    }
  ],
  "total": 1,
  "success": true
}