{
  "data": [
    {
      "id": "113012",
      "Id": "113012",
      "TinhId": 11,
      "NGAY_SINH": "05/23/2009",
      "file_name": "",
      "modified_date": "2024-06-19T08:21:27.322337",
      "NAM": "2024",
      "KY_THI": "LOP10",
      "SBD": "113012",
      "HO_TEN": "Tiêu Ngọc Diễm My",
      "TINH": "HCM",
      "TOAN": 0.75,
      "VAN": 3.5,
      "NGOAI_NGU": 2.25,
      "CHUYEN": -1,
      "TONGDIEM": 6.5,
      "SOBAODANH": "113012",
      "LI": "",
      "HOA": "",
      "SU": "",
      "DIA": "",
      "NN": 2.25,
      "GDCN": ""
    }
  ],
  "total": 1,
  "success": true
}