{
  "data": [
    {
      "id": "113209",
      "Id": "113209",
      "TinhId": 11,
      "NGAY_SINH": "08/17/2009",
      "file_name": "",
      "modified_date": "2024-06-19T08:21:27.323382",
      "NAM": "2024",
      "KY_THI": "LOP10",
      "SBD": "113209",
      "HO_TEN": "Trương Bảo Nhi",
      "TINH": "HCM",
      "TOAN": 5,
      "VAN": 6,
      "NGOAI_NGU": 7.25,
      "CHUYEN": -1,
      "TONGDIEM": 18.25,
      "SOBAODANH": "113209",
      "LI": "",
      "HOA": "",
      "SU": "",
      "DIA": "",
      "NN": 7.25,
      "GDCN": ""
    }
  ],
  "total": 1,
  "success": true
}