{
  "data": [
    {
      "id": "113462",
      "Id": "113462",
      "TinhId": 11,
      "NGAY_SINH": "07/21/2009",
      "file_name": "",
      "modified_date": "2024-06-19T08:21:27.261487",
      "NAM": "2024",
      "KY_THI": "LOP10",
      "SBD": "113462",
      "HO_TEN": "Nguyễn Hữu Tài",
      "TINH": "HCM",
      "TOAN": 5.25,
      "VAN": 7,
      "NGOAI_NGU": 6.5,
      "CHUYEN": -1,
      "TONGDIEM": 18.75,
      "SOBAODANH": "113462",
      "LI": "",
      "HOA": "",
      "SU": "",
      "DIA": "",
      "NN": 6.5,
      "GDCN": ""
    }
  ],
  "total": 1,
  "success": true
}