{
  "data": [
    {
      "id": "114145",
      "Id": "114145",
      "TinhId": 11,
      "NGAY_SINH": "10/09/2009",
      "file_name": "",
      "modified_date": "2024-06-19T08:21:27.468237",
      "NAM": "2024",
      "KY_THI": "LOP10",
      "SBD": "114145",
      "HO_TEN": "Nguyễn Huy Hoàng",
      "TINH": "HCM",
      "TOAN": 2,
      "VAN": 5.75,
      "NGOAI_NGU": 5.5,
      "CHUYEN": -1,
      "TONGDIEM": 13.25,
      "SOBAODANH": "114145",
      "LI": "",
      "HOA": "",
      "SU": "",
      "DIA": "",
      "NN": 5.5,
      "GDCN": ""
    }
  ],
  "total": 1,
  "success": true
}