{
  "data": [
    {
      "id": "115106",
      "Id": "115106",
      "TinhId": 11,
      "NGAY_SINH": "02/21/2009",
      "file_name": "",
      "modified_date": "2024-06-19T08:21:27.469943",
      "NAM": "2024",
      "KY_THI": "LOP10",
      "SBD": "115106",
      "HO_TEN": "Trần Vũ Khánh Linh",
      "TINH": "HCM",
      "TOAN": 5.75,
      "VAN": 7.25,
      "NGOAI_NGU": 6.5,
      "CHUYEN": -1,
      "TONGDIEM": 19.5,
      "SOBAODANH": "115106",
      "LI": "",
      "HOA": "",
      "SU": "",
      "DIA": "",
      "NN": 6.5,
      "GDCN": ""
    }
  ],
  "total": 1,
  "success": true
}