{
  "data": [
    {
      "id": "116107",
      "Id": "116107",
      "TinhId": 11,
      "NGAY_SINH": "02/06/2009",
      "file_name": "",
      "modified_date": "2024-06-19T08:21:27.538007",
      "NAM": "2024",
      "KY_THI": "LOP10",
      "SBD": "116107",
      "HO_TEN": "Nguyễn Thanh Phong",
      "TINH": "HCM",
      "TOAN": 3.75,
      "VAN": 6.25,
      "NGOAI_NGU": 3.25,
      "CHUYEN": -1,
      "TONGDIEM": 13.25,
      "SOBAODANH": "116107",
      "LI": "",
      "HOA": "",
      "SU": "",
      "DIA": "",
      "NN": 3.25,
      "GDCN": ""
    }
  ],
  "total": 1,
  "success": true
}