{
  "data": [
    {
      "id": "117060",
      "Id": "117060",
      "TinhId": 11,
      "NGAY_SINH": "06/23/2009",
      "file_name": "",
      "modified_date": "2024-06-19T08:21:27.603296",
      "NAM": "2024",
      "KY_THI": "LOP10",
      "SBD": "117060",
      "HO_TEN": "Trần Lê Minh Thịnh",
      "TINH": "HCM",
      "TOAN": 3.75,
      "VAN": 7,
      "NGOAI_NGU": 6,
      "CHUYEN": -1,
      "TONGDIEM": 16.75,
      "SOBAODANH": "117060",
      "LI": "",
      "HOA": "",
      "SU": "",
      "DIA": "",
      "NN": 6,
      "GDCN": ""
    }
  ],
  "total": 1,
  "success": true
}