{
  "data": [
    {
      "id": "117789",
      "Id": "117789",
      "TinhId": 11,
      "NGAY_SINH": "12/16/2009",
      "file_name": "",
      "modified_date": "2024-06-19T08:21:27.925663",
      "NAM": "2024",
      "KY_THI": "LOP10",
      "SBD": "117789",
      "HO_TEN": "Hồ Đức Phú",
      "TINH": "HCM",
      "TOAN": 5.5,
      "VAN": 5.5,
      "NGOAI_NGU": 7.75,
      "CHUYEN": -1,
      "TONGDIEM": 18.75,
      "SOBAODANH": "117789",
      "LI": "",
      "HOA": "",
      "SU": "",
      "DIA": "",
      "NN": 7.75,
      "GDCN": ""
    }
  ],
  "total": 1,
  "success": true
}