{
  "data": [
    {
      "id": "119256",
      "Id": "119256",
      "TinhId": 11,
      "NGAY_SINH": "05/02/2009",
      "file_name": "",
      "modified_date": "2024-06-19T08:21:27.857100",
      "NAM": "2024",
      "KY_THI": "LOP10",
      "SBD": "119256",
      "HO_TEN": "Nguyễn Hữu Thiện",
      "TINH": "HCM",
      "TOAN": 4.75,
      "VAN": 5.75,
      "NGOAI_NGU": 6.5,
      "CHUYEN": -1,
      "TONGDIEM": 17,
      "SOBAODANH": "119256",
      "LI": "",
      "HOA": "",
      "SU": "",
      "DIA": "",
      "NN": 6.5,
      "GDCN": ""
    }
  ],
  "total": 1,
  "success": true
}