{
  "data": [
    {
      "id": "120566",
      "Id": "120566",
      "TinhId": 12,
      "NGAY_SINH": "05/14/2009",
      "file_name": "",
      "modified_date": "2024-06-19T08:21:27.801022",
      "NAM": "2024",
      "KY_THI": "LOP10",
      "SBD": "120566",
      "HO_TEN": "Tô Ngọc Thanh Tú",
      "TINH": "HCM",
      "TOAN": 4.75,
      "VAN": 6.5,
      "NGOAI_NGU": 3,
      "CHUYEN": -1,
      "TONGDIEM": 14.25,
      "SOBAODANH": "120566",
      "LI": "",
      "HOA": "",
      "SU": "",
      "DIA": "",
      "NN": 3,
      "GDCN": ""
    }
  ],
  "total": 1,
  "success": true
}