{
  "data": [
    {
      "id": "123009",
      "Id": "123009",
      "TinhId": 12,
      "NGAY_SINH": "06/20/2009",
      "file_name": "",
      "modified_date": "2024-06-19T08:21:28.068935",
      "NAM": "2024",
      "KY_THI": "LOP10",
      "SBD": "123009",
      "HO_TEN": "Hoàng Nguyễn Trâm Anh",
      "TINH": "HCM",
      "TOAN": 4.75,
      "VAN": 7.25,
      "NGOAI_NGU": 4.25,
      "CHUYEN": -1,
      "TONGDIEM": 16.25,
      "SOBAODANH": "123009",
      "LI": "",
      "HOA": "",
      "SU": "",
      "DIA": "",
      "NN": 4.25,
      "GDCN": ""
    }
  ],
  "total": 1,
  "success": true
}