{
  "data": [
    {
      "id": "124636",
      "Id": "124636",
      "TinhId": 12,
      "NGAY_SINH": "05/18/2009",
      "file_name": "",
      "modified_date": "2024-06-19T08:21:28.136139",
      "NAM": "2024",
      "KY_THI": "LOP10",
      "SBD": "124636",
      "HO_TEN": "Hoàng Vũ Trà My",
      "TINH": "HCM",
      "TOAN": 3.25,
      "VAN": 7,
      "NGOAI_NGU": 2.75,
      "CHUYEN": -1,
      "TONGDIEM": 13,
      "SOBAODANH": "124636",
      "LI": "",
      "HOA": "",
      "SU": "",
      "DIA": "",
      "NN": 2.75,
      "GDCN": ""
    }
  ],
  "total": 1,
  "success": true
}