{
  "data": [
    {
      "id": "125883",
      "Id": "125883",
      "TinhId": 12,
      "NGAY_SINH": "03/15/2009",
      "file_name": "",
      "modified_date": "2024-06-19T08:21:28.277854",
      "NAM": "2024",
      "KY_THI": "LOP10",
      "SBD": "125883",
      "HO_TEN": "TRƯƠNG GIA HUY",
      "TINH": "HCM",
      "TOAN": 4.75,
      "VAN": 6.5,
      "NGOAI_NGU": 7.25,
      "CHUYEN": -1,
      "TONGDIEM": 18.5,
      "SOBAODANH": "125883",
      "LI": "",
      "HOA": "",
      "SU": "",
      "DIA": "",
      "NN": 7.25,
      "GDCN": ""
    }
  ],
  "total": 1,
  "success": true
}