{
  "data": [
    {
      "id": "126048",
      "Id": "126048",
      "TinhId": 12,
      "NGAY_SINH": "12/09/2009",
      "file_name": "",
      "modified_date": "2024-06-19T08:21:28.279407",
      "NAM": "2024",
      "KY_THI": "LOP10",
      "SBD": "126048",
      "HO_TEN": "HUỲNH NGUYỄN MY",
      "TINH": "HCM",
      "TOAN": 6.75,
      "VAN": 7.5,
      "NGOAI_NGU": 8,
      "CHUYEN": -1,
      "TONGDIEM": 22.25,
      "SOBAODANH": "126048",
      "LI": "",
      "HOA": "",
      "SU": "",
      "DIA": "",
      "NN": 8,
      "GDCN": ""
    }
  ],
  "total": 1,
  "success": true
}