{
  "data": [
    {
      "id": "126392",
      "Id": "126392",
      "TinhId": 12,
      "NGAY_SINH": "06/16/2009",
      "file_name": "",
      "modified_date": "2024-06-19T08:21:28.334812",
      "NAM": "2024",
      "KY_THI": "LOP10",
      "SBD": "126392",
      "HO_TEN": "Trần Ngọc Bảo Trân",
      "TINH": "HCM",
      "TOAN": 4.25,
      "VAN": 6.5,
      "NGOAI_NGU": 3.75,
      "CHUYEN": -1,
      "TONGDIEM": 14.5,
      "SOBAODANH": "126392",
      "LI": "",
      "HOA": "",
      "SU": "",
      "DIA": "",
      "NN": 3.75,
      "GDCN": ""
    }
  ],
  "total": 1,
  "success": true
}