{
  "data": [
    {
      "id": "129563",
      "Id": "129563",
      "TinhId": 12,
      "NGAY_SINH": "01/29/2009",
      "file_name": "",
      "modified_date": "2024-06-19T08:21:28.531083",
      "NAM": "2024",
      "KY_THI": "LOP10",
      "SBD": "129563",
      "HO_TEN": "Trần Gia Yến Phương",
      "TINH": "HCM",
      "TOAN": 2.5,
      "VAN": 5.5,
      "NGOAI_NGU": 4,
      "CHUYEN": -1,
      "TONGDIEM": 12,
      "SOBAODANH": "129563",
      "LI": "",
      "HOA": "",
      "SU": "",
      "DIA": "",
      "NN": 4,
      "GDCN": ""
    }
  ],
  "total": 1,
  "success": true
}