{
  "data": [
    {
      "id": "130121",
      "Id": "130121",
      "TinhId": 13,
      "NGAY_SINH": "05/26/2009",
      "file_name": "",
      "modified_date": "2024-06-19T08:21:28.609129",
      "NAM": "2024",
      "KY_THI": "LOP10",
      "SBD": "130121",
      "HO_TEN": "Vũ Huyền Diệu",
      "TINH": "HCM",
      "TOAN": 5.75,
      "VAN": 6.5,
      "NGOAI_NGU": 2.25,
      "CHUYEN": -1,
      "TONGDIEM": 14.5,
      "SOBAODANH": "130121",
      "LI": "",
      "HOA": "",
      "SU": "",
      "DIA": "",
      "NN": 2.25,
      "GDCN": ""
    }
  ],
  "total": 1,
  "success": true
}