{
  "data": [
    {
      "id": "131179",
      "Id": "131179",
      "TinhId": 13,
      "NGAY_SINH": "04/27/2009",
      "file_name": "",
      "modified_date": "2024-06-19T08:21:28.903182",
      "NAM": "2024",
      "KY_THI": "LOP10",
      "SBD": "131179",
      "HO_TEN": "Nguyễn Sơn Quỳnh Anh",
      "TINH": "HCM",
      "TOAN": 7.25,
      "VAN": 8.25,
      "NGOAI_NGU": 6.25,
      "CHUYEN": -1,
      "TONGDIEM": 21.75,
      "SOBAODANH": "131179",
      "LI": "",
      "HOA": "",
      "SU": "",
      "DIA": "",
      "NN": 6.25,
      "GDCN": ""
    }
  ],
  "total": 1,
  "success": true
}