{
  "data": [
    {
      "id": "132691",
      "Id": "132691",
      "TinhId": 13,
      "NGAY_SINH": "10/13/2009",
      "file_name": "",
      "modified_date": "2024-06-19T08:21:28.778975",
      "NAM": "2024",
      "KY_THI": "LOP10",
      "SBD": "132691",
      "HO_TEN": "Trần Quang Đạt",
      "TINH": "HCM",
      "TOAN": 5.75,
      "VAN": 7,
      "NGOAI_NGU": 6.5,
      "CHUYEN": -1,
      "TONGDIEM": 19.25,
      "SOBAODANH": "132691",
      "LI": "",
      "HOA": "",
      "SU": "",
      "DIA": "",
      "NN": 6.5,
      "GDCN": ""
    }
  ],
  "total": 1,
  "success": true
}