{
  "data": [
    {
      "id": "135411",
      "Id": "135411",
      "TinhId": 13,
      "NGAY_SINH": "06/11/2009",
      "file_name": "",
      "modified_date": "2024-06-19T08:21:28.969379",
      "NAM": "2024",
      "KY_THI": "LOP10",
      "SBD": "135411",
      "HO_TEN": "Lưu Triệu Khang",
      "TINH": "HCM",
      "TOAN": 3.75,
      "VAN": 7,
      "NGOAI_NGU": 8,
      "CHUYEN": -1,
      "TONGDIEM": 18.75,
      "SOBAODANH": "135411",
      "LI": "",
      "HOA": "",
      "SU": "",
      "DIA": "",
      "NN": 8,
      "GDCN": ""
    }
  ],
  "total": 1,
  "success": true
}