{
  "data": [
    {
      "id": "135654",
      "Id": "135654",
      "TinhId": 13,
      "NGAY_SINH": "04/28/2009",
      "file_name": "",
      "modified_date": "2024-06-19T08:21:28.908251",
      "NAM": "2024",
      "KY_THI": "LOP10",
      "SBD": "135654",
      "HO_TEN": "Hoàng Thành Nhân",
      "TINH": "HCM",
      "TOAN": 5.25,
      "VAN": 7,
      "NGOAI_NGU": 6.25,
      "CHUYEN": -1,
      "TONGDIEM": 18.5,
      "SOBAODANH": "135654",
      "LI": "",
      "HOA": "",
      "SU": "",
      "DIA": "",
      "NN": 6.25,
      "GDCN": ""
    }
  ],
  "total": 1,
  "success": true
}