{
  "data": [
    {
      "id": "136216",
      "Id": "136216",
      "TinhId": 13,
      "NGAY_SINH": "07/18/2009",
      "file_name": "",
      "modified_date": "2024-06-19T08:21:29.235377",
      "NAM": "2024",
      "KY_THI": "LOP10",
      "SBD": "136216",
      "HO_TEN": "Dương Gia Bảo",
      "TINH": "HCM",
      "TOAN": 7.5,
      "VAN": 8.25,
      "NGOAI_NGU": 9.5,
      "CHUYEN": -1,
      "TONGDIEM": 25.25,
      "SOBAODANH": "136216",
      "LI": "",
      "HOA": "",
      "SU": "",
      "DIA": "",
      "NN": 9.5,
      "GDCN": ""
    }
  ],
  "total": 1,
  "success": true
}