{
  "data": [
    {
      "id": "136781",
      "Id": "136781",
      "TinhId": 13,
      "NGAY_SINH": "09/23/2008",
      "file_name": "",
      "modified_date": "2024-06-19T08:21:29.033681",
      "NAM": "2024",
      "KY_THI": "LOP10",
      "SBD": "136781",
      "HO_TEN": "Nguyễn Trần Quốc Minh",
      "TINH": "HCM",
      "TOAN": 5,
      "VAN": 6.75,
      "NGOAI_NGU": 3.75,
      "CHUYEN": -1,
      "TONGDIEM": 15.5,
      "SOBAODANH": "136781",
      "LI": "",
      "HOA": "",
      "SU": "",
      "DIA": "",
      "NN": 3.75,
      "GDCN": ""
    }
  ],
  "total": 1,
  "success": true
}