{
  "data": [
    {
      "id": "137758",
      "Id": "137758",
      "TinhId": 13,
      "NGAY_SINH": "10/09/2009",
      "file_name": "",
      "modified_date": "2024-06-19T08:21:29.104921",
      "NAM": "2024",
      "KY_THI": "LOP10",
      "SBD": "137758",
      "HO_TEN": "Huỳnh Trung Hải",
      "TINH": "HCM",
      "TOAN": 8.25,
      "VAN": 6.5,
      "NGOAI_NGU": 9,
      "CHUYEN": -1,
      "TONGDIEM": 23.75,
      "SOBAODANH": "137758",
      "LI": "",
      "HOA": "",
      "SU": "",
      "DIA": "",
      "NN": 9,
      "GDCN": ""
    }
  ],
  "total": 1,
  "success": true
}