{
  "data": [
    {
      "id": "138152",
      "Id": "138152",
      "TinhId": 13,
      "NGAY_SINH": "09/28/2009",
      "file_name": "",
      "modified_date": "2024-06-19T08:21:29.099060",
      "NAM": "2024",
      "KY_THI": "LOP10",
      "SBD": "138152",
      "HO_TEN": "Hoàng Nguyễn Ái Nhi",
      "TINH": "HCM",
      "TOAN": -1,
      "VAN": -1,
      "NGOAI_NGU": -1,
      "CHUYEN": -1,
      "TONGDIEM": 0,
      "SOBAODANH": "138152",
      "LI": "",
      "HOA": "",
      "SU": "",
      "DIA": "",
      "NN": -1,
      "GDCN": ""
    }
  ],
  "total": 1,
  "success": true
}