{
  "data": [
    {
      "id": "140596",
      "Id": "140596",
      "TinhId": 14,
      "NGAY_SINH": "11/26/2009",
      "file_name": "",
      "modified_date": "2024-06-19T08:21:29.521536",
      "NAM": "2024",
      "KY_THI": "LOP10",
      "SBD": "140596",
      "HO_TEN": "Nguyễn Lâm Minh Khang",
      "TINH": "HCM",
      "TOAN": 3.25,
      "VAN": 5,
      "NGOAI_NGU": 3.75,
      "CHUYEN": -1,
      "TONGDIEM": 12,
      "SOBAODANH": "140596",
      "LI": "",
      "HOA": "",
      "SU": "",
      "DIA": "",
      "NN": 3.75,
      "GDCN": ""
    }
  ],
  "total": 1,
  "success": true
}