{
  "data": [
    {
      "id": "141184",
      "Id": "141184",
      "TinhId": 14,
      "NGAY_SINH": "11/12/2009",
      "file_name": "",
      "modified_date": "2024-06-19T08:21:29.376309",
      "NAM": "2024",
      "KY_THI": "LOP10",
      "SBD": "141184",
      "HO_TEN": "Hồ Phan Thanh Phúc",
      "TINH": "HCM",
      "TOAN": 7.25,
      "VAN": 6.5,
      "NGOAI_NGU": 8.5,
      "CHUYEN": -1,
      "TONGDIEM": 22.25,
      "SOBAODANH": "141184",
      "LI": "",
      "HOA": "",
      "SU": "",
      "DIA": "",
      "NN": 8.5,
      "GDCN": ""
    }
  ],
  "total": 1,
  "success": true
}