{
  "data": [
    {
      "id": "145320",
      "Id": "145320",
      "TinhId": 14,
      "NGAY_SINH": "08/08/2009",
      "file_name": "",
      "modified_date": "2024-06-19T08:21:29.306268",
      "NAM": "2024",
      "KY_THI": "LOP10",
      "SBD": "145320",
      "HO_TEN": "Trịnh Lê Hoài Phúc",
      "TINH": "HCM",
      "TOAN": 8,
      "VAN": 6.75,
      "NGOAI_NGU": 8.75,
      "CHUYEN": -1,
      "TONGDIEM": 23.5,
      "SOBAODANH": "145320",
      "LI": "",
      "HOA": "",
      "SU": "",
      "DIA": "",
      "NN": 8.75,
      "GDCN": ""
    }
  ],
  "total": 1,
  "success": true
}