{
  "data": [
    {
      "id": "149551",
      "Id": "149551",
      "TinhId": 14,
      "NGAY_SINH": "07/21/2009",
      "file_name": "",
      "modified_date": "2024-06-19T08:21:29.944038",
      "NAM": "2024",
      "KY_THI": "LOP10",
      "SBD": "149551",
      "HO_TEN": "Quan Thiên Hồng Ngọc",
      "TINH": "HCM",
      "TOAN": 5,
      "VAN": 6.75,
      "NGOAI_NGU": 8.5,
      "CHUYEN": -1,
      "TONGDIEM": 20.25,
      "SOBAODANH": "149551",
      "LI": "",
      "HOA": "",
      "SU": "",
      "DIA": "",
      "NN": 8.5,
      "GDCN": ""
    }
  ],
  "total": 1,
  "success": true
}