{
  "data": [
    {
      "id": "150348",
      "Id": "150348",
      "TinhId": 15,
      "NGAY_SINH": "03/08/2009",
      "file_name": "",
      "modified_date": "2024-06-19T08:21:30.042170",
      "NAM": "2024",
      "KY_THI": "LOP10",
      "SBD": "150348",
      "HO_TEN": "Nguyễn Đức Duy",
      "TINH": "HCM",
      "TOAN": 5,
      "VAN": 6.5,
      "NGOAI_NGU": 4.25,
      "CHUYEN": -1,
      "TONGDIEM": 15.75,
      "SOBAODANH": "150348",
      "LI": "",
      "HOA": "",
      "SU": "",
      "DIA": "",
      "NN": 4.25,
      "GDCN": ""
    }
  ],
  "total": 1,
  "success": true
}