{
  "data": [
    {
      "id": "155557",
      "Id": "155557",
      "TinhId": 15,
      "NGAY_SINH": "12/21/2009",
      "file_name": "",
      "modified_date": "2024-06-19T08:21:30.504960",
      "NAM": "2024",
      "KY_THI": "LOP10",
      "SBD": "155557",
      "HO_TEN": "HUỲNH DUY TÂN",
      "TINH": "HCM",
      "TOAN": 3.5,
      "VAN": 8,
      "NGOAI_NGU": 8.5,
      "CHUYEN": -1,
      "TONGDIEM": 20,
      "SOBAODANH": "155557",
      "LI": "",
      "HOA": "",
      "SU": "",
      "DIA": "",
      "NN": 8.5,
      "GDCN": ""
    }
  ],
  "total": 1,
  "success": true
}