{
  "data": [
    {
      "id": "155795",
      "Id": "155795",
      "TinhId": 15,
      "NGAY_SINH": "11/13/2009",
      "file_name": "",
      "modified_date": "2024-06-19T08:21:30.374350",
      "NAM": "2024",
      "KY_THI": "LOP10",
      "SBD": "155795",
      "HO_TEN": "Nguyễn Hoàng Trúc Anh",
      "TINH": "HCM",
      "TOAN": 6.5,
      "VAN": 7,
      "NGOAI_NGU": 7.25,
      "CHUYEN": -1,
      "TONGDIEM": 20.75,
      "SOBAODANH": "155795",
      "LI": "",
      "HOA": "",
      "SU": "",
      "DIA": "",
      "NN": 7.25,
      "GDCN": ""
    }
  ],
  "total": 1,
  "success": true
}