{
  "data": [
    {
      "id": "156237",
      "Id": "156237",
      "TinhId": 15,
      "NGAY_SINH": "10/19/2009",
      "file_name": "",
      "modified_date": "2024-06-19T08:21:30.375100",
      "NAM": "2024",
      "KY_THI": "LOP10",
      "SBD": "156237",
      "HO_TEN": "Nguyễn Thanh Ngân",
      "TINH": "HCM",
      "TOAN": 6.25,
      "VAN": 7.75,
      "NGOAI_NGU": 8.5,
      "CHUYEN": -1,
      "TONGDIEM": 22.5,
      "SOBAODANH": "156237",
      "LI": "",
      "HOA": "",
      "SU": "",
      "DIA": "",
      "NN": 8.5,
      "GDCN": ""
    }
  ],
  "total": 1,
  "success": true
}