{
  "data": [
    {
      "id": "157696",
      "Id": "157696",
      "TinhId": 15,
      "NGAY_SINH": "07/13/2008",
      "file_name": "",
      "modified_date": "2024-06-19T08:21:30.703659",
      "NAM": "2024",
      "KY_THI": "LOP10",
      "SBD": "157696",
      "HO_TEN": "Dương Thành Hưng",
      "TINH": "HCM",
      "TOAN": 4.75,
      "VAN": 4,
      "NGOAI_NGU": 2.25,
      "CHUYEN": -1,
      "TONGDIEM": 11,
      "SOBAODANH": "157696",
      "LI": "",
      "HOA": "",
      "SU": "",
      "DIA": "",
      "NN": 2.25,
      "GDCN": ""
    }
  ],
  "total": 1,
  "success": true
}