{
  "data": [
    {
      "id": "159364",
      "Id": "159364",
      "TinhId": 15,
      "NGAY_SINH": "03/08/2009",
      "file_name": "",
      "modified_date": "2024-06-19T08:21:30.954196",
      "NAM": "2024",
      "KY_THI": "LOP10",
      "SBD": "159364",
      "HO_TEN": "Lương Nhã Kỳ",
      "TINH": "HCM",
      "TOAN": 2.25,
      "VAN": 5.25,
      "NGOAI_NGU": 4,
      "CHUYEN": -1,
      "TONGDIEM": 11.5,
      "SOBAODANH": "159364",
      "LI": "",
      "HOA": "",
      "SU": "",
      "DIA": "",
      "NN": 4,
      "GDCN": ""
    }
  ],
  "total": 1,
  "success": true
}