{
  "data": [
    {
      "id": "160010",
      "Id": "160010",
      "TinhId": 16,
      "NGAY_SINH": "08/26/2009",
      "file_name": "",
      "modified_date": "2024-06-19T08:21:30.828906",
      "NAM": "2024",
      "KY_THI": "LOP10",
      "SBD": "160010",
      "HO_TEN": "Châu Quốc Huy",
      "TINH": "HCM",
      "TOAN": 4.75,
      "VAN": 7,
      "NGOAI_NGU": 4.5,
      "CHUYEN": -1,
      "TONGDIEM": 16.25,
      "SOBAODANH": "160010",
      "LI": "",
      "HOA": "",
      "SU": "",
      "DIA": "",
      "NN": 4.5,
      "GDCN": ""
    }
  ],
  "total": 1,
  "success": true
}