{
  "data": [
    {
      "id": "160656",
      "Id": "160656",
      "TinhId": 16,
      "NGAY_SINH": "10/01/2009",
      "file_name": "",
      "modified_date": "2024-06-19T08:21:31.017376",
      "NAM": "2024",
      "KY_THI": "LOP10",
      "SBD": "160656",
      "HO_TEN": "Nguyễn Ngọc Bảo Châu",
      "TINH": "HCM",
      "TOAN": 5.75,
      "VAN": 8.5,
      "NGOAI_NGU": 7.5,
      "CHUYEN": -1,
      "TONGDIEM": 21.75,
      "SOBAODANH": "160656",
      "LI": "",
      "HOA": "",
      "SU": "",
      "DIA": "",
      "NN": 7.5,
      "GDCN": ""
    }
  ],
  "total": 1,
  "success": true
}