{
  "data": [
    {
      "id": "162007",
      "Id": "162007",
      "TinhId": 16,
      "NGAY_SINH": "10/21/2009",
      "file_name": "",
      "modified_date": "2024-06-19T08:21:30.958943",
      "NAM": "2024",
      "KY_THI": "LOP10",
      "SBD": "162007",
      "HO_TEN": "Nguyễn Phạm Hoàng Lân",
      "TINH": "HCM",
      "TOAN": 5,
      "VAN": 3.75,
      "NGOAI_NGU": 3.25,
      "CHUYEN": -1,
      "TONGDIEM": 12,
      "SOBAODANH": "162007",
      "LI": "",
      "HOA": "",
      "SU": "",
      "DIA": "",
      "NN": 3.25,
      "GDCN": ""
    }
  ],
  "total": 1,
  "success": true
}