{
  "data": [
    {
      "id": "164796",
      "Id": "164796",
      "TinhId": 16,
      "NGAY_SINH": "04/18/2009",
      "file_name": "",
      "modified_date": "2024-06-19T08:21:31.098490",
      "NAM": "2024",
      "KY_THI": "LOP10",
      "SBD": "164796",
      "HO_TEN": "Phan Ngọc Tường Vy",
      "TINH": "HCM",
      "TOAN": 2,
      "VAN": 5,
      "NGOAI_NGU": 3.25,
      "CHUYEN": -1,
      "TONGDIEM": 10.25,
      "SOBAODANH": "164796",
      "LI": "",
      "HOA": "",
      "SU": "",
      "DIA": "",
      "NN": 3.25,
      "GDCN": ""
    }
  ],
  "total": 1,
  "success": true
}