{
  "data": [
    {
      "id": "164813",
      "Id": "164813",
      "TinhId": 16,
      "NGAY_SINH": "08/14/2009",
      "file_name": "",
      "modified_date": "2024-06-19T08:21:31.232823",
      "NAM": "2024",
      "KY_THI": "LOP10",
      "SBD": "164813",
      "HO_TEN": "Nguyễn Duy An",
      "TINH": "HCM",
      "TOAN": 2.75,
      "VAN": 3.5,
      "NGOAI_NGU": 3,
      "CHUYEN": -1,
      "TONGDIEM": 9.25,
      "SOBAODANH": "164813",
      "LI": "",
      "HOA": "",
      "SU": "",
      "DIA": "",
      "NN": 3,
      "GDCN": ""
    }
  ],
  "total": 1,
  "success": true
}