{
  "data": [
    {
      "id": "166561",
      "Id": "166561",
      "TinhId": 16,
      "NGAY_SINH": "01/10/2009",
      "file_name": "",
      "modified_date": "2024-06-19T08:21:31.297056",
      "NAM": "2024",
      "KY_THI": "LOP10",
      "SBD": "166561",
      "HO_TEN": "Nguyễn Hoàng Anh Thư",
      "TINH": "HCM",
      "TOAN": 5,
      "VAN": 7.5,
      "NGOAI_NGU": 9.75,
      "CHUYEN": -1,
      "TONGDIEM": 22.25,
      "SOBAODANH": "166561",
      "LI": "",
      "HOA": "",
      "SU": "",
      "DIA": "",
      "NN": 9.75,
      "GDCN": ""
    }
  ],
  "total": 1,
  "success": true
}