{
  "data": [
    {
      "id": "167078",
      "Id": "167078",
      "TinhId": 16,
      "NGAY_SINH": "03/07/2009",
      "file_name": "",
      "modified_date": "2024-06-19T08:21:31.361353",
      "NAM": "2024",
      "KY_THI": "LOP10",
      "SBD": "167078",
      "HO_TEN": "Khổng Thiên Bảo",
      "TINH": "HCM",
      "TOAN": 3,
      "VAN": 3.25,
      "NGOAI_NGU": 3.25,
      "CHUYEN": -1,
      "TONGDIEM": 9.5,
      "SOBAODANH": "167078",
      "LI": "",
      "HOA": "",
      "SU": "",
      "DIA": "",
      "NN": 3.25,
      "GDCN": ""
    }
  ],
  "total": 1,
  "success": true
}