{
  "data": [
    {
      "id": "167561",
      "Id": "167561",
      "TinhId": 16,
      "NGAY_SINH": "08/27/2009",
      "file_name": "",
      "modified_date": "2024-06-19T08:21:31.369427",
      "NAM": "2024",
      "KY_THI": "LOP10",
      "SBD": "167561",
      "HO_TEN": "Lương Thị Quỳnh Giao",
      "TINH": "HCM",
      "TOAN": 4,
      "VAN": 7,
      "NGOAI_NGU": 3.5,
      "CHUYEN": -1,
      "TONGDIEM": 14.5,
      "SOBAODANH": "167561",
      "LI": "",
      "HOA": "",
      "SU": "",
      "DIA": "",
      "NN": 3.5,
      "GDCN": ""
    }
  ],
  "total": 1,
  "success": true
}