{
  "data": [
    {
      "id": "171219",
      "Id": "171219",
      "TinhId": 17,
      "NGAY_SINH": "06/02/2009",
      "file_name": "",
      "modified_date": "2024-06-19T08:21:31.683352",
      "NAM": "2024",
      "KY_THI": "LOP10",
      "SBD": "171219",
      "HO_TEN": "NGUYỄN HẢI NAM",
      "TINH": "HCM",
      "TOAN": 2.5,
      "VAN": 5.5,
      "NGOAI_NGU": 3,
      "CHUYEN": -1,
      "TONGDIEM": 11,
      "SOBAODANH": "171219",
      "LI": "",
      "HOA": "",
      "SU": "",
      "DIA": "",
      "NN": 3,
      "GDCN": ""
    }
  ],
  "total": 1,
  "success": true
}