{
  "data": [
    {
      "id": "174086",
      "Id": "174086",
      "TinhId": 17,
      "NGAY_SINH": "05/08/2009",
      "file_name": "",
      "modified_date": "2024-06-19T08:21:31.618321",
      "NAM": "2024",
      "KY_THI": "LOP10",
      "SBD": "174086",
      "HO_TEN": "TRẦN HỮU ĐẠT",
      "TINH": "HCM",
      "TOAN": 2,
      "VAN": 5,
      "NGOAI_NGU": 0.75,
      "CHUYEN": -1,
      "TONGDIEM": 7.75,
      "SOBAODANH": "174086",
      "LI": "",
      "HOA": "",
      "SU": "",
      "DIA": "",
      "NN": 0.75,
      "GDCN": ""
    }
  ],
  "total": 1,
  "success": true
}