{
  "data": [
    {
      "id": "175496",
      "Id": "175496",
      "TinhId": 17,
      "NGAY_SINH": "05/26/2009",
      "file_name": "",
      "modified_date": "2024-06-19T08:21:31.553774",
      "NAM": "2024",
      "KY_THI": "LOP10",
      "SBD": "175496",
      "HO_TEN": "NGUYỄN HẢI YẾN",
      "TINH": "HCM",
      "TOAN": 5.75,
      "VAN": 6.75,
      "NGOAI_NGU": 8.75,
      "CHUYEN": -1,
      "TONGDIEM": 21.25,
      "SOBAODANH": "175496",
      "LI": "",
      "HOA": "",
      "SU": "",
      "DIA": "",
      "NN": 8.75,
      "GDCN": ""
    }
  ],
  "total": 1,
  "success": true
}