{
  "data": [
    {
      "id": "175887",
      "Id": "175887",
      "TinhId": 17,
      "NGAY_SINH": "08/26/2009",
      "file_name": "",
      "modified_date": "2024-06-19T08:21:31.992120",
      "NAM": "2024",
      "KY_THI": "LOP10",
      "SBD": "175887",
      "HO_TEN": "BÙI NGỌC HIỀN",
      "TINH": "HCM",
      "TOAN": 7.5,
      "VAN": 6.75,
      "NGOAI_NGU": 9,
      "CHUYEN": -1,
      "TONGDIEM": 23.25,
      "SOBAODANH": "175887",
      "LI": "",
      "HOA": "",
      "SU": "",
      "DIA": "",
      "NN": 9,
      "GDCN": ""
    }
  ],
  "total": 1,
  "success": true
}