{
  "data": [
    {
      "id": "177413",
      "Id": "177413",
      "TinhId": 17,
      "NGAY_SINH": "11/08/2009",
      "file_name": "",
      "modified_date": "2024-06-19T08:21:32.202546",
      "NAM": "2024",
      "KY_THI": "LOP10",
      "SBD": "177413",
      "HO_TEN": "Huỳnh Mai Khanh",
      "TINH": "HCM",
      "TOAN": 2.75,
      "VAN": 5.75,
      "NGOAI_NGU": 5.5,
      "CHUYEN": -1,
      "TONGDIEM": 14,
      "SOBAODANH": "177413",
      "LI": "",
      "HOA": "",
      "SU": "",
      "DIA": "",
      "NN": 5.5,
      "GDCN": ""
    }
  ],
  "total": 1,
  "success": true
}