{
  "data": [
    {
      "id": "178410",
      "Id": "178410",
      "TinhId": 17,
      "NGAY_SINH": "10/22/2009",
      "file_name": "",
      "modified_date": "2024-06-19T08:21:32.135007",
      "NAM": "2024",
      "KY_THI": "LOP10",
      "SBD": "178410",
      "HO_TEN": "Lương Chí Quang",
      "TINH": "HCM",
      "TOAN": 4,
      "VAN": 6.75,
      "NGOAI_NGU": 6.75,
      "CHUYEN": -1,
      "TONGDIEM": 17.5,
      "SOBAODANH": "178410",
      "LI": "",
      "HOA": "",
      "SU": "",
      "DIA": "",
      "NN": 6.75,
      "GDCN": ""
    }
  ],
  "total": 1,
  "success": true
}