{
  "data": [
    {
      "id": "188066",
      "Id": "188066",
      "TinhId": 18,
      "NGAY_SINH": "10/16/2009",
      "file_name": "",
      "modified_date": "2024-06-19T08:21:33.052095",
      "NAM": "2024",
      "KY_THI": "LOP10",
      "SBD": "188066",
      "HO_TEN": "Đinh Mạnh Hùng",
      "TINH": "HCM",
      "TOAN": 3.25,
      "VAN": 5,
      "NGOAI_NGU": 4,
      "CHUYEN": -1,
      "TONGDIEM": 12.25,
      "SOBAODANH": "188066",
      "LI": "",
      "HOA": "",
      "SU": "",
      "DIA": "",
      "NN": 4,
      "GDCN": ""
    }
  ],
  "total": 1,
  "success": true
}