{
  "data": [
    {
      "id": "189520",
      "Id": "189520",
      "TinhId": 18,
      "NGAY_SINH": "10/29/2009",
      "file_name": "",
      "modified_date": "2024-06-19T08:21:32.862335",
      "NAM": "2024",
      "KY_THI": "LOP10",
      "SBD": "189520",
      "HO_TEN": "TRỊNH CẨM TÚ",
      "TINH": "HCM",
      "TOAN": 1,
      "VAN": 5.5,
      "NGOAI_NGU": 4.5,
      "CHUYEN": -1,
      "TONGDIEM": 11,
      "SOBAODANH": "189520",
      "LI": "",
      "HOA": "",
      "SU": "",
      "DIA": "",
      "NN": 4.5,
      "GDCN": ""
    }
  ],
  "total": 1,
  "success": true
}