{
  "data": [
    {
      "id": "189805",
      "Id": "189805",
      "TinhId": 18,
      "NGAY_SINH": "05/15/2009",
      "file_name": "",
      "modified_date": "2024-06-19T08:21:33.051121",
      "NAM": "2024",
      "KY_THI": "LOP10",
      "SBD": "189805",
      "HO_TEN": "Nguyễn Văn Quốc Bảo",
      "TINH": "HCM",
      "TOAN": 5.75,
      "VAN": 6.75,
      "NGOAI_NGU": 5.5,
      "CHUYEN": -1,
      "TONGDIEM": 18,
      "SOBAODANH": "189805",
      "LI": "",
      "HOA": "",
      "SU": "",
      "DIA": "",
      "NN": 5.5,
      "GDCN": ""
    }
  ],
  "total": 1,
  "success": true
}