{
  "data": [
    {
      "id": "190429",
      "Id": "190429",
      "TinhId": 19,
      "NGAY_SINH": "12/29/2009",
      "file_name": "",
      "modified_date": "2024-06-19T08:21:32.993284",
      "NAM": "2024",
      "KY_THI": "LOP10",
      "SBD": "190429",
      "HO_TEN": "Nguyễn Đăng Khoa",
      "TINH": "HCM",
      "TOAN": 6,
      "VAN": 6,
      "NGOAI_NGU": 7,
      "CHUYEN": -1,
      "TONGDIEM": 19,
      "SOBAODANH": "190429",
      "LI": "",
      "HOA": "",
      "SU": "",
      "DIA": "",
      "NN": 7,
      "GDCN": ""
    }
  ],
  "total": 1,
  "success": true
}