{
  "data": [
    {
      "id": "191486",
      "Id": "191486",
      "TinhId": 19,
      "NGAY_SINH": "07/27/2009",
      "file_name": "",
      "modified_date": "2024-06-19T08:21:32.931123",
      "NAM": "2024",
      "KY_THI": "LOP10",
      "SBD": "191486",
      "HO_TEN": "Phạm Gia Thư",
      "TINH": "HCM",
      "TOAN": 2,
      "VAN": 4.75,
      "NGOAI_NGU": 3.5,
      "CHUYEN": -1,
      "TONGDIEM": 10.25,
      "SOBAODANH": "191486",
      "LI": "",
      "HOA": "",
      "SU": "",
      "DIA": "",
      "NN": 3.5,
      "GDCN": ""
    }
  ],
  "total": 1,
  "success": true
}